README.md
setup.py
bin/sausage-machine-version.py
sausage_machine/__init__.py
sausage_machine.egg-info/PKG-INFO
sausage_machine.egg-info/SOURCES.txt
sausage_machine.egg-info/dependency_links.txt
sausage_machine.egg-info/requires.txt
sausage_machine.egg-info/top_level.txt
test/test_nothing.py