Metadata-Version: 1.1
Name: sausage-machine
Version: 0.0.1
Summary: A Python class for running / scheduling pipeline jobs
Home-page: https://github.com/VirologyCharite/sausage-machine
Author: Terry Jones
Author-email: tcj25@cam.ac.uk
License: MIT
Download-URL: https://github.com/VirologyCharite/sausage-machine
Keywords: pipeline
Platform: UNKNOWN
Classifier: Programming Language :: Python :: 2.7
Classifier: Programming Language :: Python :: 3
Classifier: Development Status :: 4 - Beta
Classifier: Intended Audience :: Developers
Classifier: License :: OSI Approved :: MIT License
Classifier: Operating System :: OS Independent
Classifier: Topic :: Software Development :: Libraries :: Python Modules
